Workbook
Name Slicer_Category: #N/A
Name Slicer_Category1: #N/A
Name Slicer_Month: #N/A
Name Slicer_Payment_Mode: #N/A
Name Slicer_Subcategory: #N/A

Sheet Raw Data
A1: Expense_ID | B1: Expense_Date | C1: Category | D1: Description | E1: Payment_Mode | F1: Amount | G1: Subcategory | H1: Location | I1: Recurring | J1: Vendor | K1: Payment_Status | L1: Notes
A2: 1 | B2: 45965.323 | C2: Shopping | D2: Sample expense 1 | E2: Card | F2: 3986.17 | G2: Electronics | H2: New York | I2: Yes | J2: Macy's | K2: Paid | L2: -
A3: 2 | B3: 46042.323 | C3: Medical | D3: Sample expense 2 | E3: Card | F3: 1390.62 | G3: Health Insurance | H3: Chicago | I3: No | J3: Walgreens | K3: Pending | L3: -
A4: 3 | B4: 45955.323 | C4: Food | D4: Sample expense 3 | E4: UPI | F4: 2222.91 | G4: Beverages | H4: Phoenix | I4: No | J4: Walmart | K4: Paid | L4: -
A5: 4 | B5: 45877.323 | C5: Shopping | D5: Sample expense 4 | E5: Card | F5: 438.36 | G5: Accessories | H5: Phoenix | I5: No | J5: Macy's | K5: Paid | L5: -
A6: 5 | B6: 45969.323 | C6: Medical | D6: Sample expense 5 | E6: Cash | F6: 175.49 | G6: Pharmacy | H6: Houston | I6: Yes | J6: Walgreens | K6: Paid | L6: -
A7: 6 | B7: 45934.323 | C7: Utilities | D7: Sample expense 6 | E7: UPI | F7: 4815.11 | G7: Internet | H7: Miami | I7: No | J7: Verizon | K7: Paid | L7: -
A8: 7 | B8: 45883.323 | C8: Utilities | D8: Sample expense 7 | E8: Cash | F8: 4188.1 | G8: Electricity | H8: New York | I8: No | J8: ComEd | K8: Paid | L8: -
A9: 8 | B9: 45965.323 | C9: Utilities | D9: Sample expense 8 | E9: Cash | F9: 3495.07 | G9: Internet | H9: New York | I9: No | J9: ComEd | K9: Paid | L9: -
A10: 9 | B10: 45984.323 | C10: Utilities | D10: Sample expense 9 | E10: Card | F10: 2074.32 | G10: Electricity | H10: Los Angeles | I10: No | J10: City Water | K10: Paid | L10: -
A11: 10 | B11: 45937.323 | C11: Utilities | D11: Sample expense 10 | E11: Card | F11: 907.81 | G11: Internet | H11: Houston | I11: No | J11: GasCo | K11: Paid | L11: -
A12: 11 | B12: 45950.323 | C12: Medical | D12: Sample expense 11 | E12: Card | F12: 824.36 | G12: Pharmacy | H12: Los Angeles | I12: Yes | J12: City Hospital | K12: Paid | L12: -
A13: 12 | B13: 45979.323 | C13: Medical | D13: Sample expense 12 | E13: Card | F13: 1288.7 | G13: Health Insurance | H13: Los Angeles | I13: No | J13: HealthCare Inc | K13: Paid | L13: -
... A151: 150 | B151: 46032.323 | C151: Food | D151: Sample expense 150 | E151: UPI | F151: 2369.87 | G151: Restaurant | H151: Houston | I151: No | J151: Domino's | K151: Paid | L151: -

Sheet Cleaned data
A1: Expense_ID | B1: Expense_Date | C1: Category | D1: Description | E1: Payment_Mode | F1: Amount | G1: Subcategory | H1: Location | I1: Recurring | J1: Vendor | K1: Payment_Status | L1: Notes | M1: Month | N1: YEAR | O1: Hgh-Value-Flag
A2: 1 | B2: 45965 | C2: Shopping | D2: Sample expense 1 | E2: Card | F2: 3986.17 | G2: Electronics | H2: New York | I2: Yes | J2: Macy's | K2: Paid | L2: - | M2: =TEXT(B2,"mmmm") -> November | N2: =YEAR(B2) -> 2025 | O2: =IF(F2>3000,"high","normal") -> high
A3: 2 | B3: 46042 | C3: Medical | D3: Sample expense 2 | E3: Card | F3: 1390.62 | G3: Health Insurance | H3: Chicago | I3: No | J3: Walgreens | K3: Pending | L3: - | M3: =TEXT(B3,"mmmm") -> January | N3: =YEAR(B3) -> 2026 | O3: =IF(F3>3000,"high","normal") -> normal
A4: 3 | B4: 45955 | C4: Food | D4: Sample expense 3 | E4: UPI | F4: 2222.91 | G4: Beverages | H4: Phoenix | I4: No | J4: Walmart | K4: Paid | L4: - | M4: =TEXT(B4,"mmmm") -> October | N4: =YEAR(B4) -> 2025 | O4: =IF(F4>3000,"high","normal") -> normal
A5: 4 | B5: 45877 | C5: Shopping | D5: Sample expense 4 | E5: Card | F5: 438.36 | G5: Accessories | H5: Phoenix | I5: No | J5: Macy's | K5: Paid | L5: - | M5: =TEXT(B5,"mmmm") -> August | N5: =YEAR(B5) -> 2025 | O5: =IF(F5>3000,"high","normal") -> normal
A6: 5 | B6: 45969 | C6: Medical | D6: Sample expense 5 | E6: Cash | F6: 175.49 | G6: Pharmacy | H6: Houston | I6: Yes | J6: Walgreens | K6: Paid | L6: - | M6: =TEXT(B6,"mmmm") -> November | N6: =YEAR(B6) -> 2025 | O6: =IF(F6>3000,"high","normal") -> normal
A7: 6 | B7: 45934 | C7: Utilities | D7: Sample expense 6 | E7: UPI | F7: 4815.11 | G7: Internet | H7: Miami | I7: No | J7: Verizon | K7: Paid | L7: - | M7: =TEXT(B7,"mmmm") -> October | N7: =YEAR(B7) -> 2025 | O7: =IF(F7>3000,"high","normal") -> high
A8: 7 | B8: 45883 | C8: Utilities | D8: Sample expense 7 | E8: Cash | F8: 4188.1 | G8: Electricity | H8: New York | I8: No | J8: ComEd | K8: Paid | L8: - | M8: =TEXT(B8,"mmmm") -> August | N8: =YEAR(B8) -> 2025 | O8: =IF(F8>3000,"high","normal") -> high
A9: 8 | B9: 45965 | C9: Utilities | D9: Sample expense 8 | E9: Cash | F9: 3495.07 | G9: Internet | H9: New York | I9: No | J9: ComEd | K9: Paid | L9: - | M9: =TEXT(B9,"mmmm") -> November | N9: =YEAR(B9) -> 2025 | O9: =IF(F9>3000,"high","normal") -> high
A10: 9 | B10: 45984 | C10: Utilities | D10: Sample expense 9 | E10: Card | F10: 2074.32 | G10: Electricity | H10: Los Angeles | I10: No | J10: City Water | K10: Paid | L10: - | M10: =TEXT(B10,"mmmm") -> November | N10: =YEAR(B10) -> 2025 | O10: =IF(F10>3000,"high","normal") -> normal
A11: 10 | B11: 45937 | C11: Utilities | D11: Sample expense 10 | E11: Card | F11: 907.81 | G11: Internet | H11: Houston | I11: No | J11: GasCo | K11: Paid | L11: - | M11: =TEXT(B11,"mmmm") -> October | N11: =YEAR(B11) -> 2025 | O11: =IF(F11>3000,"high","normal") -> normal
A12: 11 | B12: 45950 | C12: Medical | D12: Sample expense 11 | E12: Card | F12: 824.36 | G12: Pharmacy | H12: Los Angeles | I12: Yes | J12: City Hospital | K12: Paid | L12: - | M12: =TEXT(B12,"mmmm") -> October | N12: =YEAR(B12) -> 2025 | O12: =IF(F12>3000,"high","normal") -> normal
A13: 12 | B13: 45979 | C13: Medical | D13: Sample expense 12 | E13: Card | F13: 1288.7 | G13: Health Insurance | H13: Los Angeles | I13: No | J13: HealthCare Inc | K13: Paid | L13: - | M13: =TEXT(B13,"mmmm") -> November | N13: =YEAR(B13) -> 2025 | O13: =IF(F13>3000,"high","normal") -> normal
... A151: 150 | B151: 46032 | C151: Food | D151: Sample expense 150 | E151: UPI | F151: 2369.87 | G151: Restaurant | H151: Houston | I151: No | J151: Domino's | K151: Paid | L151: - | M151: =TEXT(B151,"mmmm") -> January | N151: =YEAR(B151) -> 2026 | O151: =IF(F151>3000,"high","normal") -> normal

Sheet calculations
A1: Total Expense | C1: Month | D1: Monthly Total | E1: Monthly % | G1: Category | H1: Total Expences | I1: % of Share | K1: Payment_Mode | L1: Total Spend | N1: Expense_Date | O1: Cumulative Expences
A2: =SUM('Cleaned data'!F:F) -> 373159.22 | C2: November | D2: =SUMIFS('Cleaned data'!F:F,'Cleaned data'!M:M,calculations!C2) -> 40165.73 | E2: =Table1[[#This Row],[Monthly Total]]/$A$2 -> 0.10763698 | G2: Shopping | H2: =SUMIFS('Cleaned data'!F:F,'Cleaned data'!C:C,calculations!G2) -> 25427.91 | I2: =H2/$A$2 -> 0.068142253 | K2: Card | L2: =SUMIFS('Cleaned data'!F:F,'Cleaned data'!E:E,calculations!K2) -> 133107.1 | N2: 45965 | O2: =SUM('Cleaned data'!F1:F1:'Cleaned data'!F2) -> 3986.17
C3: January | D3: =SUMIFS('Cleaned data'!F:F,'Cleaned data'!M:M,calculations!C3) -> 28485.58 | E3: =Table1[[#This Row],[Monthly Total]]/$A$2 -> 0.076336262 | G3: Medical | H3: =SUMIFS('Cleaned data'!F:F,'Cleaned data'!C:C,calculations!G3) -> 51240.79 | I3: =H3/$A$2 -> 0.13731616 | K3: UPI | L3: =SUMIFS('Cleaned data'!F:F,'Cleaned data'!E:E,calculations!K3) -> 114922.83 | N3: 46042 | O3: =SUM('Cleaned data'!F2:F2:'Cleaned data'!F3) -> 5376.79
C4: October | D4: =SUMIFS('Cleaned data'!F:F,'Cleaned data'!M:M,calculations!C4) -> 64382.41 | E4: =Table1[[#This Row],[Monthly Total]]/$A$2 -> 0.17253335 | G4: Food | H4: =SUMIFS('Cleaned data'!F:F,'Cleaned data'!C:C,calculations!G4) -> 79972.26 | I4: =H4/$A$2 -> 0.21431136 | K4: Cash | L4: =SUMIFS('Cleaned data'!F:F,'Cleaned data'!E:E,calculations!K4) -> 125129.29 | N4: 45955 | O4: =SUM('Cleaned data'!F3:F3:'Cleaned data'!F4) -> 3613.53
C5: August | D5: =SUMIFS('Cleaned data'!F:F,'Cleaned data'!M:M,calculations!C5) -> 67939.72 | E5: =Table1[[#This Row],[Monthly Total]]/$A$2 -> 0.1820663 | G5: Utilities | H5: =SUMIFS('Cleaned data'!F:F,'Cleaned data'!C:C,calculations!G5) -> 65266.48 | I5: =H5/$A$2 -> 0.1749025 | N5: 45877 | O5: =SUM('Cleaned data'!F4:F4:'Cleaned data'!F5) -> 2661.27
C6: December | D6: =SUMIFS('Cleaned data'!F:F,'Cleaned data'!M:M,calculations!C6) -> 75715.97 | E6: =Table1[[#This Row],[Monthly Total]]/$A$2 -> 0.20290526 | G6: Travel | H6: =SUMIFS('Cleaned data'!F:F,'Cleaned data'!C:C,calculations!G6) -> 63013.39 | I6: =H6/$A$2 -> 0.16886462 | K6: Payment mode analysis | N6: 45969 | O6: =SUM('Cleaned data'!F5:F5:'Cleaned data'!F6) -> 613.85
C7: September | D7: =SUMIFS('Cleaned data'!F:F,'Cleaned data'!M:M,calculations!C7) -> 79596.04 | E7: =Table1[[#This Row],[Monthly Total]]/$A$2 -> 0.21330316 | G7: Rent | H7: =SUMIFS('Cleaned data'!F:F,'Cleaned data'!C:C,calculations!G7) -> 34284.67 | I7: =H7/$A$2 -> 0.091876787 | N7: 45934 | O7: =SUM('Cleaned data'!F6:F6:'Cleaned data'!F7) -> 4990.6
C8: July | D8: =SUMIFS('Cleaned data'!F:F,'Cleaned data'!M:M,calculations!C8) -> 16873.77 | E8: =Table1[[#This Row],[Monthly Total]]/$A$2 -> 0.045218687 | G8: Entertainment | H8: =SUMIFS('Cleaned data'!F:F,'Cleaned data'!C:C,calculations!G8) -> 53953.72 | I8: =H8/$A$2 -> 0.14458632 | N8: 45883 | O8: =SUM('Cleaned data'!F7:F7:'Cleaned data'!F8) -> 9003.21
C9: Monthly Expences Calculation | N9: 45984 | O9: =SUM('Cleaned data'!F8:F8:'Cleaned data'!F9) -> 7683.17
G10: Category wise Expense Calculation | N10: 45937 | O10: =SUM('Cleaned data'!F9:F9:'Cleaned data'!F10) -> 5569.39
N11: 45950 | O11: =SUM('Cleaned data'!F10:F10:'Cleaned data'!F11) -> 2982.13
N12: 45979 | O12: =SUM('Cleaned data'!F11:F11:'Cleaned data'!F12) -> 1732.17
N13: 45962 | O13: =SUM('Cleaned data'!F12:F12:'Cleaned data'!F13) -> 2113.06
C14: Average monthly calculations | K14: High value Transactions | N14: 45966 | O14: =SUM('Cleaned data'!F13:F13:'Cleaned data'!F14) -> 4057.37
C15: =AVERAGE(Table5[Amount],Table5[Month]) -> 2487.7281 | K15: =COUNTIF('Cleaned data'!O:O,"HIGH") -> 63 | N15: 46014 | O15: =SUM('Cleaned data'!F14:F14:'Cleaned data'!F15) -> 6355.92
N16: 45993 | O16: =SUM('Cleaned data'!F15:F15:'Cleaned data'!F16) -> 6905.23
N17: 46012 | O17: =SUM('Cleaned data'!F16:F16:'Cleaned data'!F17) -> 4753.65
N18: 45915 | O18: =SUM('Cleaned data'!F17:F17:'Cleaned data'!F18) -> 6212.25
N19: 45864 | O19: =SUM('Cleaned data'!F18:F18:'Cleaned data'!F19) -> 8479.17
N20: 46020 | O20: =SUM('Cleaned data'!F19:F19:'Cleaned data'!F20) -> 6496.64
N21: 45900 | O21: =SUM('Cleaned data'!F20:F20:'Cleaned data'!F21) -> 5872.07
N22: 45992 | O22: =SUM('Cleaned data'!F21:F21:'Cleaned data'!F22) -> 5205.04
N23: 46023 | O23: =SUM('Cleaned data'!F22:F22:'Cleaned data'!F23) -> 3403.29
N24: 45920 | O24: =SUM('Cleaned data'!F23:F23:'Cleaned data'!F24) -> 3088.33
N25: 45884 | O25: =SUM('Cleaned data'!F24:F24:'Cleaned data'!F25) -> 5613.4
N26: 45951 | O26: =SUM('Cleaned data'!F25:F25:'Cleaned data'!F26) -> 3922.59
N27: 45911 | O27: =SUM('Cleaned data'!F26:F26:'Cleaned data'!F27) -> 745.81
... N102: 45928 | O102: =SUM('Cleaned data'!F101:F101:'Cleaned data'!F102) -> 4635.29

Sheet created pivot tables
A3: Row Labels | B3: Sum of Amount | D3: Row Labels | E3: Sum of Amount | G3: Row Labels | H3: Sum of Amount | J3: Row Labels | K3: Sum of Amount
A4: January | B4: 28485.58 | D4: Card | E4: 133107.1 | G4: January | H4: 28485.58 | J4: Shopping | K4: 25427.91
A5: July | B5: 16873.77 | D5: Cash | E5: 125129.29 | G5: July | H5: 16873.77 | J5: Rent | K5: 34284.67
A6: August | B6: 67939.72 | D6: UPI | E6: 114922.83 | G6: August | H6: 67939.72 | J6: Medical | K6: 51240.79 | R6: Row Labels | S6: Sum of Amount
A7: September | B7: 79596.04 | D7: Grand Total | E7: 373159.22 | G7: September | H7: 79596.04 | J7: Entertainment | K7: 53953.72 | R7: Concert | S7: 15332.98
A8: October | B8: 64382.41 | G8: October | H8: 64382.41 | J8: Travel | K8: 63013.39 | R8: Games | S8: 7446.52
A9: November | B9: 40165.73 | G9: November | H9: 40165.73 | J9: Utilities | K9: 65266.48 | R9: Movies | S9: 18350.73
A10: December | B10: 75715.97 | G10: December | H10: 75715.97 | J10: Food | K10: 79972.26 | R10: Subscription | S10: 12823.49
A11: Grand Total | B11: 373159.22 | G11: Grand Total | H11: 373159.22 | J11: Grand Total | K11: 373159.22 | R11: Grand Total | S11: 53953.72

Sheet recommended pt
A3: Row Labels | B3: Sum of Amount | D3: Sum of Amount | E3: Column Labels | I3: Count of Expense_ID | J3: Column Labels
A4: Card | B4: 133107.1 | D4: Row Labels | E4: No | F4: Yes | G4: Grand Total | I4: Row Labels | J4: No | K4: Yes | L4: Grand Total
A5: Cash | B5: 125129.29 | D5: Chicago | E5: 65157.57 | F5: 17965.76 | G5: 83123.33 | I5: January | J5: 11 | K5: 6 | L5: 17
A6: UPI | B6: 114922.83 | D6: Houston | E6: 27332.01 | F6: 6751.52 | G6: 34083.53 | I6: July | J6: 5 | K6: 1 | L6: 6
A7: Grand Total | B7: 373159.22 | D7: Los Angeles | E7: 69647.75 | F7: 5101.43 | G7: 74749.18 | I7: August | J7: 24 | K7: 5 | L7: 29
D8: Miami | E8: 69892.38 | F8: 8715.68 | G8: 78608.06 | I8: September | J8: 22 | K8: 6 | L8: 28
D9: New York | E9: 43399.5 | F9: 12424.64 | G9: 55824.14 | I9: October | J9: 19 | K9: 6 | L9: 25
D10: Phoenix | E10: 30507.44 | F10: 16263.54 | G10: 46770.98 | I10: November | J10: 16 | K10: 3 | L10: 19
D11: Grand Total | E11: 305936.65 | F11: 67222.57 | G11: 373159.22 | I11: December | J11: 21 | K11: 5 | L11: 26
I12: Grand Total | J12: 118 | K12: 32 | L12: 150
D15: Count of Expense_ID | E15: Column Labels
D16: Row Labels | E16: Paid | F16: Pending | G16: Grand Total
D17: Entertainment | E17: 16 | F17: 1 | G17: 17
D18: Food | E18: 32 | F18: 1 | G18: 33
D19: Medical | E19: 19 | F19: 2 | G19: 21
D20: Rent | E20: 14 | F20: 1 | G20: 15
D21: Shopping | E21: 11 | G21: 11
D22: Travel | E22: 22 | F22: 3 | G22: 25
D23: Utilities | E23: 24 | F23: 4 | G23: 28
D24: Grand Total | E24: 138 | F24: 12 | G24: 150

Sheet dashboard
